Topsis_Sudhit_102017137/Sudhit_102017137.py
Topsis_Sudhit_102017137-0.1.dist-info/METADATA
Topsis_Sudhit_102017137-0.1.dist-info/WHEEL
Topsis_Sudhit_102017137-0.1.dist-info/entry_points.txt
Topsis_Sudhit_102017137-0.1.dist-info/top_level.txt
Topsis_Sudhit_102017137-0.1.dist-info/RECORD
