Metadata-Version: 2.1
Name: Topsis-Sudhit-102017137
Version: 0.1
Summary: This is a topsis package of version 0.1
Home-page: UNKNOWN
Author: Sudhit Soni
Author-email: soni_be20@thapar.edu
License: UNKNOWN
Platform: UNKNOWN
Requires-Dist: pandas
